mpcrl/__init__.py
mpcrl/agents/lstd_dpg.py
mpcrl/agents/lstd_q_learning.py
mpcrl/agents/common/agent.py
mpcrl/agents/common/globopt_learning_agent.py
mpcrl/agents/common/learning_agent.py
mpcrl/agents/common/rl_learning_agent.py
mpcrl/core/__init__.py
mpcrl/core/callbacks.py
mpcrl/core/errors.py
mpcrl/core/experience.py
mpcrl/core/exploration.py
mpcrl/core/parameters.py
mpcrl/core/schedulers.py
mpcrl/core/update.py
mpcrl/core/warmstart.py
mpcrl/optim/__init__.py
mpcrl/optim/adam.py
mpcrl/optim/base_optimizer.py
mpcrl/optim/gradient_based_optimizer.py
mpcrl/optim/gradient_descent.py
mpcrl/optim/gradient_free_optimizer.py
mpcrl/optim/newton_method.py
mpcrl/optim/rmsprop.py
mpcrl/util/__init__.py
mpcrl/util/control.py
mpcrl/util/geometry.py
mpcrl/util/iters.py
mpcrl/util/math.py
mpcrl/util/named.py
mpcrl/util/seeding.py
mpcrl/wrappers/__init__.py
mpcrl/wrappers/agents/__init__.py
mpcrl/wrappers/agents/evaluate.py
mpcrl/wrappers/agents/log.py
mpcrl/wrappers/agents/record_updates.py
mpcrl/wrappers/agents/wrapper.py
mpcrl/wrappers/envs/__init__.py
mpcrl/wrappers/envs/monitor_episodes.py
mpcrl/wrappers/envs/monitor_infos.py
mpcrl-1.4.1.dist-info/licenses/LICENSE
mpcrl-1.4.1.dist-info/METADATA
mpcrl-1.4.1.dist-info/WHEEL
mpcrl-1.4.1.dist-info/top_level.txt
mpcrl-1.4.1.dist-info/RECORD
