Metadata-Version: 2.4
Name: mpcrl
Version: 1.4.1
Summary: Reinforcement Learning with Model Predictive Control
Author-email: Filippo Airaldi <filippoairaldi@gmail.com>
License-Expression: MIT
Project-URL: Homepage, https://github.com/FilippoAiraldi/mpc-reinforcement-learning
Project-URL: Bug Tracker, https://github.com/FilippoAiraldi/mpc-reinforcement-learning/issues
Keywords: reinforcement-learning,model-predictive-control,optimization,casadi
Classifier: Programming Language :: Python
Classifier: Programming Language :: Python :: 3 :: Only
Classifier: Programming Language :: Python :: 3.9
Classifier: Programming Language :: Python :: 3.10
Classifier: Programming Language :: Python :: 3.11
Classifier: Programming Language :: Python :: 3.12
Classifier: Programming Language :: Python :: 3.13
Classifier: Operating System :: OS Independent
Classifier: Intended Audience :: Science/Research
Classifier: Topic :: Scientific/Engineering :: Mathematics
Classifier: Topic :: Scientific/Engineering :: Artificial Intelligence
Requires-Python: >=3.9
License-File: LICENSE
Requires-Dist: typing_extensions>=4.5.0; python_version <= "3.9"
Requires-Dist: numba>=0.57.1
Requires-Dist: csnlp!=1.7.0rc1,>=1.6.8
Requires-Dist: scipy>=1.11.0
Requires-Dist: gymnasium>=0.28.1
Dynamic: license-file
